mypdns/__init__.py
Spirillen-0.0.1.dev0.dist-info/LICENSE
Spirillen-0.0.1.dev0.dist-info/METADATA
Spirillen-0.0.1.dev0.dist-info/WHEEL
Spirillen-0.0.1.dev0.dist-info/top_level.txt
Spirillen-0.0.1.dev0.dist-info/RECORD
