Metadata-Version: 2.1
Name: Spirillen
Version: 0.0.1.dev0
Summary: Name space reservation
Home-page: https://www.mypdns.org/
Author: spirillen
Author-email: spirillen@protonmail.com
License: UNKNOWN
Project-URL: Tracker, https://www.mypdns.org/
Project-URL: Source, https://github.com/pypa/sampleproject/
Platform: UNKNOWN
Classifier: Programming Language :: Python :: 3
Classifier: License :: OSI Approved :: GNU Lesser General Public License v2 or later (LGPLv2+)
Classifier: Operating System :: POSIX :: Linux
Requires-Python: >=3.7
